README.md
setup.py
src/warprnnt_op.cc
warprnnt_tensorflow/__init__.py
warprnnt_tensorflow.egg-info/PKG-INFO
warprnnt_tensorflow.egg-info/SOURCES.txt
warprnnt_tensorflow.egg-info/dependency_links.txt
warprnnt_tensorflow.egg-info/top_level.txt